normal_corner/__init__.py
normal_corner/normal_corner.py
normal_corner-0.0.1.dist-info/LICENSE
normal_corner-0.0.1.dist-info/METADATA
normal_corner-0.0.1.dist-info/WHEEL
normal_corner-0.0.1.dist-info/top_level.txt
normal_corner-0.0.1.dist-info/RECORD
