Metadata-Version: 2.1
Name: normal-corner
Version: 0.0.1
Summary: Analytical corner plot for Gaussian distributions
Home-page: https://github.com/bvgoncharov/normal_corner
Author: Boris Goncharov
Author-email: goncharov.boris@physics.msu.ru
License: UNKNOWN
Platform: UNKNOWN
Classifier: Programming Language :: Python :: 3
Classifier: License :: OSI Approved :: MIT License
Classifier: Operating System :: OS Independent
Requires-Dist: numpy
Requires-Dist: scipy
Requires-Dist: matplotlib
